gradiv/__init__.py
gradiv/_version.py
gradiv/algo.py
gradiv/functions.py
gradiv/main.py
gradiv/pggraph.py
gradiv/polymorphism.py
gradiv/tests.py
gradiv-0.1.0.dist-info/licenses/LICENSE
gradiv-0.1.0.dist-info/METADATA
gradiv-0.1.0.dist-info/WHEEL
gradiv-0.1.0.dist-info/entry_points.txt
gradiv-0.1.0.dist-info/top_level.txt
gradiv-0.1.0.dist-info/RECORD
