Metadata-Version: 2.4
Name: GraDiv
Version: 0.1.0
Summary: GraDiv is a tool to lead diversity analysis on a pangenome graph. It allows users to call variants from a pangenome graph indexed with GraTools, then compute diversity statistics from them.
Author-email: "Margaux Imbert (UM)" <margaux.imbert01@etu.umontpellier.fr>, "Stéphane De Mita (PHIM, INRAE)" <stephane.demita@inrae.fr>, "Ravel Sebastien (PHIM, CIRAD)" <sebastien.ravel@cirad.fr>, "Christine Tranchant (DIADE, IRD)" <christine.tranchant@cirad.fr>
License:                     GNU GENERAL PUBLIC LICENSE
Project-URL: Homepage, https://forge.ird.fr/phim/gradiv
Keywords: pangenome,graph,diversity
Classifier: Development Status :: 4 - Beta
Classifier: Intended Audience :: Developers
Classifier: Intended Audience :: End Users/Desktop
Classifier: Natural Language :: English
Classifier: Operating System :: POSIX :: Linux
Classifier: Programming Language :: Python :: 3.10
Classifier: Programming Language :: Python :: 3.11
Classifier: Programming Language :: Python :: 3.12
Classifier: Programming Language :: Python :: 3.13
Classifier: Topic :: Scientific/Engineering
Classifier: Topic :: Scientific/Engineering :: Bio-Informatics
Requires-Python: >=3.10
License-File: LICENSE
Requires-Dist: pybedtools
Requires-Dist: pysam
Requires-Dist: click>=8.0.3
Requires-Dist: click_extra
Requires-Dist: egglib>=3.5.0
Requires-Dist: rich
Dynamic: license-file
